tsflow/__init__.py
tsflow/chem.py
tsflow/mcd.py
tsflow/run.py
tsflow/Calculator/__init__.py
tsflow/Calculator/gaussian.py
tsflow/Calculator/orca.py
tsflow/Calculator/template.py
tsflow/utils/__init__.py
tsflow/utils/ic.py
tsflow/utils/process.py
tsflow-0.1.0.dist-info/LICENSE
tsflow-0.1.0.dist-info/METADATA
tsflow-0.1.0.dist-info/WHEEL
tsflow-0.1.0.dist-info/entry_points.txt
tsflow-0.1.0.dist-info/top_level.txt
tsflow-0.1.0.dist-info/RECORD
